colorsator/__init__.py
colorsator-0.1.dist-info/METADATA
colorsator-0.1.dist-info/WHEEL
colorsator-0.1.dist-info/top_level.txt
colorsator-0.1.dist-info/RECORD
