Metadata-Version: 2.1
Name: colorsator
Version: 0.1
Summary: zertyzerty
Home-page: UNKNOWN
Author: colorsator
Author-email: zertyzerty@gmail.com
License: UNKNOWN
Platform: UNKNOWN
Classifier: Programming Language :: Python :: 3
Classifier: License :: OSI Approved :: MIT License
Classifier: Operating System :: OS Independent
